{
  "NEED_CLEAR_CACHE": false,
  "COURSE_TRAININGS": "[{\"uuid\":\"3be87c72-7772-420a-a901-29d350616a32\",\"name\":\"Stress resistance\",\"description\":\"Stress resistance\",\"retryDelayHours\":72,\"timeToFailHours\":240,\"trainingsTotalCount\":25,\"trainingsCompletedCount\":0,\"trainings\":[{\"uuid\":\"e5a46172-99b8-4338-b3da-06e2dc43bec5\",\"name\":\"Step 1\",\"description\":\"Stress resistance\",\"duration\":9,\"retryDelayHours\":1,\"delay\":20,\"progresses\":[],\"retries\":0,\"isFinished\":false,\"isSuccessful\":false,\"focusState\":0},{\"uuid\":\"dea7864b-566f-43ab-afcf-d14cf733cb15\",\"name\":\"Step 2\",\"description\":\"Stress resistance\",\"duration\":9,\"retryDelayHours\":1,\"delay\":20,\"progresses\":[],\"retries\":0,\"isFinished\":false,\"isSuccessful\":false,\"focusState\":0},{\"uuid\":\"fd40a497-6014-4aea-9e36-2cd0a751bb5b\",\"name\":\"Step 3\",\"description\":\"Stress resistance\",\"duration\":9,\"retryDelayHours\":1,\"delay\":20,\"progresses\":[],\"retries\":0,\"isFinished\":false,\"isSuccessful\":false,\"focusState\":0},{\"uuid\":\"d062b1da-077f-4245-97b4-eba3108c3371\",\"name\":\"Step 4\",\"description\":\"Stress resistance\",\"duration\":9,\"retryDelayHours\":1,\"delay\":20,\"progresses\":[],\"retries\":0,\"isFinished\":false,\"isSuccessful\":false,\"focusState\":0},{\"uuid\":\"c4dd1eeb-2647-48ca-998f-7fbc24aed426\",\"name\":\"Step 5\",\"description\":\"Stress resistance\",\"duration\":9,\"retryDelayHours\":1,\"delay\":20,\"progresses\":[],\"retries\":0,\"isFinished\":false,\"isSuccessful\":false,\"focusState\":0},{\"uuid\":\"a2416f88-c164-4c36-b7dc-861f1176ad24\",\"name\":\"Step 6\",\"description\":\"Stress resistance\",\"duration\":9,\"retryDelayHours\":1,\"delay\":20,\"progresses\":[],\"retries\":0,\"isFinished\":false,\"isSuccessful\":false,\"focusState\":0},{\"uuid\":\"ab084f56-2d82-4e99-9ae8-07b84553ef60\",\"name\":\"Step 7\",\"description\":\"Stress resistance\",\"duration\":9,\"retryDelayHours\":1,\"delay\":20,\"progresses\":[],\"retries\":0,\"isFinished\":false,\"isSuccessful\":false,\"focusState\":0},{\"uuid\":\"315cd451-d047-4b33-8296-caaecb95c37d\",\"name\":\"Step 8\",\"description\":\"Stress resistance\",\"duration\":9,\"retryDelayHours\":1,\"delay\":20,\"progresses\":[],\"retries\":0,\"isFinished\":false,\"isSuccessful\":false,\"focusState\":0},{\"uuid\":\"d72edd2d-4413-48d8-b29f-680c49201b81\",\"name\":\"Step 9\",\"description\":\"Stress resistance\",\"duration\":9,\"retryDelayHours\":1,\"delay\":20,\"progresses\":[],\"retries\":0,\"isFinished\":false,\"isSuccessful\":false,\"focusState\":0},{\"uuid\":\"aa74e50a-0c69-4399-9c6c-b0a14c2fc434\",\"name\":\"Step 10\",\"description\":\"Stress resistance\",\"duration\":9,\"retryDelayHours\":1,\"delay\":20,\"progresses\":[],\"retries\":0,\"isFinished\":false,\"isSuccessful\":false,\"focusState\":0},{\"uuid\":\"1bb8ce5e-132a-456a-9a60-3d683f309ef4\",\"name\":\"Step 11\",\"description\":\"Stress resistance\",\"duration\":9,\"retryDelayHours\":1,\"delay\":20,\"progresses\":[],\"retries\":0,\"isFinished\":false,\"isSuccessful\":false,\"focusState\":0},{\"uuid\":\"c3834aae-c3fd-469a-a448-1cc167bfbb72\",\"name\":\"Step 12\",\"description\":\"Stress resistance\",\"duration\":9,\"retryDelayHours\":1,\"delay\":20,\"progresses\":[],\"retries\":0,\"isFinished\":false,\"isSuccessful\":false,\"focusState\":0},{\"uuid\":\"02967ecc-635a-4cbb-83d8-2c9cd7bf8048\",\"name\":\"Step 13\",\"description\":\"Stress resistance\",\"duration\":9,\"retryDelayHours\":1,\"delay\":20,\"progresses\":[],\"retries\":0,\"isFinished\":false,\"isSuccessful\":false,\"focusState\":0},{\"uuid\":\"4469be3a-d083-4c44-ab70-29edb714a8c3\",\"name\":\"Step 14\",\"description\":\"Stress resistance\",\"duration\":9,\"retryDelayHours\":1,\"delay\":20,\"progresses\":[],\"retries\":0,\"isFinished\":false,\"isSuccessful\":false,\"focusState\":0},{\"uuid\":\"53de163d-21b2-45e8-9411-9e9a7c22110e\",\"name\":\"Step 15\",\"description\":\"Stress resistance\",\"duration\":9,\"retryDelayHours\":1,\"delay\":20,\"progresses\":[],\"retries\":0,\"isFinished\":false,\"isSuccessful\":false,\"focusState\":0},{\"uuid\":\"b280f1d2-e3a7-4733-a24c-2a3b47f76488\",\"name\":\"Step 16\",\"description\":\"Stress resistance\",\"duration\":9,\"retryDelayHours\":1,\"delay\":20,\"progresses\":[],\"retries\":0,\"isFinished\":false,\"isSuccessful\":false,\"focusState\":0},{\"uuid\":\"93ecaad7-3c52-4585-a34e-0b9727d67f61\",\"name\":\"Step 17\",\"description\":\"Stress resistance\",\"duration\":9,\"retryDelayHours\":1,\"delay\":20,\"progresses\":[],\"retries\":0,\"isFinished\":false,\"isSuccessful\":false,\"focusState\":0},{\"uuid\":\"14caa88d-e519-4556-b3f0-47ca2ede7960\",\"name\":\"Step 18\",\"description\":\"Stress resistance\",\"duration\":9,\"retryDelayHours\":1,\"delay\":20,\"progresses\":[],\"retries\":0,\"isFinished\":false,\"isSuccessful\":false,\"focusState\":0},{\"uuid\":\"256731ab-2bfe-4c74-8255-29e1e749a751\",\"name\":\"Step 19\",\"description\":\"Stress resistance\",\"duration\":9,\"retryDelayHours\":1,\"delay\":20,\"progresses\":[],\"retries\":0,\"isFinished\":false,\"isSuccessful\":false,\"focusState\":0},{\"uuid\":\"04f29942-2c60-4f12-91c0-466b78349ad5\",\"name\":\"Step 20\",\"description\":\"Stress resistance\",\"duration\":9,\"retryDelayHours\":1,\"delay\":20,\"progresses\":[],\"retries\":0,\"isFinished\":false,\"isSuccessful\":false,\"focusState\":0},{\"uuid\":\"dde16adb-51be-4029-b0cc-5ff68e4b1ba8\",\"name\":\"Step 21\",\"description\":\"Stress resistance\",\"duration\":9,\"retryDelayHours\":1,\"delay\":20,\"progresses\":[],\"retries\":0,\"isFinished\":false,\"isSuccessful\":false,\"focusState\":0},{\"uuid\":\"4adb3bd5-5c15-4f1f-8509-56163549bc04\",\"name\":\"Step 22\",\"description\":\"Stress resistance\",\"duration\":9,\"retryDelayHours\":1,\"delay\":20,\"progresses\":[],\"retries\":0,\"isFinished\":false,\"isSuccessful\":false,\"focusState\":0},{\"uuid\":\"a75ac7d8-be5f-4554-8e9a-811bb8599a9c\",\"name\":\"Step 23\",\"description\":\"Stress resistance\",\"duration\":9,\"retryDelayHours\":1,\"delay\":20,\"progresses\":[],\"retries\":0,\"isFinished\":false,\"isSuccessful\":false,\"focusState\":0},{\"uuid\":\"bda2008e-7f73-40e1-850f-885bb31502bc\",\"name\":\"Step 24\",\"description\":\"Stress resistance\",\"duration\":9,\"retryDelayHours\":1,\"delay\":20,\"progresses\":[],\"retries\":0,\"isFinished\":false,\"isSuccessful\":false,\"focusState\":0},{\"uuid\":\"cd425062-b621-4ead-92a0-b671e7a11a87\",\"name\":\"Step 25\",\"description\":\"Stress resistance\",\"duration\":9,\"retryDelayHours\":1,\"delay\":20,\"progresses\":[],\"retries\":0,\"isFinished\":false,\"isSuccessful\":false,\"focusState\":0}],\"profileCourses\":[{\"trainingsCompletedCount\":0}]}]",
  "QUICK_TRAININGS": "[{\"uuid\":\"e0923356-365c-40fa-b739-58b3be16f4e6\",\"duration\":25,\"training_type\":\"e0923356-365c-40fa-b739-58b3be16f4e6\"},{\"uuid\":\"aa41da60-dce2-48b3-8c1c-1b3b088e1bb7\",\"duration\":6,\"training_type\":\"aa41da60-dce2-48b3-8c1c-1b3b088e1bb7\"},{\"uuid\":\"6a12a158-80e8-4056-baaa-c2f30ca2ef5e\",\"duration\":25,\"training_type\":\"6a12a158-80e8-4056-baaa-c2f30ca2ef5e\"},{\"uuid\":\"0075f259-3226-4140-9cf1-11155939b3c2\",\"duration\":25,\"training_type\":\"0075f259-3226-4140-9cf1-11155939b3c2\"},{\"uuid\":\"fe187150-624b-43c6-bccd-1e3cefba7244\",\"duration\":10,\"training_type\":\"fe187150-624b-43c6-bccd-1e3cefba7244\"},{\"uuid\":\"4b765c28-a054-4c96-a819-e79e03057ef0\",\"duration\":10,\"training_type\":\"4b765c28-a054-4c96-a819-e79e03057ef0\"},{\"uuid\":\"b9386ab6-792e-4419-97bc-ecd746866b20\",\"duration\":10,\"training_type\":\"b9386ab6-792e-4419-97bc-ecd746866b20\"},{\"uuid\":\"17c78e9b-a661-46a0-986d-de3253b02e84\",\"duration\":25,\"training_type\":\"17c78e9b-a661-46a0-986d-de3253b02e84\"}]",
  "PLAYLISTS": "[{\"name\":\"Central Park\",\"sampleUrl\":\"https://s3-mind-tracker.storage.yandexcloud.net/samples/prod/8d6c34746307fea743503972bb7c9a7013e48045720f53730fc4ef71ffb1b9c4.mp3\",\"imageUrl\":\"https://s3-mind-tracker.storage.yandexcloud.net/images/prod/fae337758cfb479e9bfdeabdbe3f14860df6c754c4888f44b998827637b25b32.jpg\",\"playlistTracks\":[{\"trackOrder\":0,\"track\":{\"name\":\"central_park_birds\",\"settings\":{\"change\":\"positive_feedback\"},\"url\":\"https://s3-mind-tracker.storage.yandexcloud.net/tracks/prod/82f525edd808113d3cd9e485d7e187ee2aa2fb9f83b7afa9ef9b3255dffa2344.mp3\",\"translationLanguages\":[]}},{\"trackOrder\":0,\"track\":{\"name\":\"central_park_highway\",\"settings\":{\"change\":\"negative_feedback\"},\"url\":\"https://s3-mind-tracker.storage.yandexcloud.net/tracks/prod/19a7eb7a8f4454b305d60cde0d947d1d892a33e851b3f8ec509c5dcb0bb23219.mp3\",\"translationLanguages\":[]}},{\"trackOrder\":0,\"track\":{\"name\":\"central_park_background\",\"settings\":{\"change\":\"background\"},\"url\":\"https://s3-mind-tracker.storage.yandexcloud.net/tracks/prod/250c4c24198ec5e4ffd373ba074105ca3b650a214a1421aa9eb7f1b17be65d66.mp3\",\"translationLanguages\":[]}},{\"trackOrder\":0,\"track\":{\"name\":\"central_park_wind\",\"settings\":{\"change\":\"positive_feedback_fast\"},\"url\":\"https://s3-mind-tracker.storage.yandexcloud.net/tracks/prod/96628ce26da946ba97722abad5059c1d45e39106c12941fcd24dae9600f3f133.mp3\",\"translationLanguages\":[]}}],\"translationLanguages\":[{\"title\":\"Central Park\",\"description\":\"When you have the right level of relaxation, you will hear the birds singing. Otherwise, the noise of the highway.\",\"language\":{\"name\":\"english\",\"isoCode\":\"en\"}},{\"title\":\"Parque central\",\"description\":\"Cuando tengas el nivel adecuado de relajación, escucharás el canto de los pájaros. De lo contrario, ruido de la carretera.\",\"language\":{\"name\":\"Español\",\"isoCode\":\"es\"}},{\"title\":\"Центральный парк\",\"description\":\"Когда у вас нужный уровень релаксации, вы будете слышать пение птиц. Иначе - шум шоссе.\",\"language\":{\"name\":\"russian\",\"isoCode\":\"ru\"}}],\"training_type\":\"training\"},{\"name\":\"Morning by the sea\",\"sampleUrl\":\"https://s3-mind-tracker.storage.yandexcloud.net/samples/prod/fd60c333b569aea756bdbace007e33decc796d50430007ed15114a361dbc5269.mp3\",\"imageUrl\":\"https://s3-mind-tracker.storage.yandexcloud.net/images/prod/872bf01b413010e373ae801c969bd8802de058cb3c7e53e9a6088b3e133e2926.jpg\",\"playlistTracks\":[{\"trackOrder\":0,\"track\":{\"name\":\"morning_sea_surf\",\"settings\":{\"change\":\"positive_feedback\"},\"url\":\"https://s3-mind-tracker.storage.yandexcloud.net/tracks/prod/62a78cc17d52a7441f0032466c7c11b80fbb436e9f9207fccbb2abc1d200f6f1.mp3\",\"translationLanguages\":[]}},{\"trackOrder\":0,\"track\":{\"name\":\"morning_sea_seagulls\",\"settings\":{\"change\":\"negative_feedback\"},\"url\":\"https://s3-mind-tracker.storage.yandexcloud.net/tracks/prod/78ea07c3fb0d96e758e72072ba36fd902b068f36f0887eebc784431a1dbc1307.mp3\",\"translationLanguages\":[]}}],\"translationLanguages\":[{\"title\":\"Mañana junto al mar\",\"description\":\"Cuando estés en el nivel adecuado de relajación, escucharás el sonido de las olas. De lo contrario, el grito de las gaviotas.\",\"language\":{\"name\":\"Español\",\"isoCode\":\"es\"}},{\"title\":\"Утро у моря\",\"description\":\"Когда у вас нужный уровень релаксации, вы будете слышать шум прибоя. Иначе - крик чаек.\",\"language\":{\"name\":\"russian\",\"isoCode\":\"ru\"}},{\"title\":\"Morning by the sea\",\"description\":\"When you have the right level of relaxation, you will hear the sound of the surf. Otherwise - the cry of seagulls.\",\"language\":{\"name\":\"english\",\"isoCode\":\"en\"}}],\"training_type\":\"training\"},{\"name\":\"Kitten\",\"sampleUrl\":\"https://s3-mind-tracker.storage.yandexcloud.net/samples/prod/8e67850671297b0f5c568c561e5ad6d0838d161096df04e3d9192bcca21e1fec.mp3\",\"imageUrl\":\"https://s3-mind-tracker.storage.yandexcloud.net/images/prod/f5dbcd1105a40e7162e9e0064b8dfb02f281ce793e3b788846ee4eaf05f25a4e.jpg\",\"playlistTracks\":[{\"trackOrder\":0,\"track\":{\"name\":\"kitten_cat_purring\",\"settings\":{\"change\":\"positive_feedback\"},\"url\":\"https://s3-mind-tracker.storage.yandexcloud.net/tracks/prod/a375712d563da9d56479ab04e65bd2012faba043cbe2df92511a28ee21eff9d7.mp3\",\"translationLanguages\":[]}},{\"trackOrder\":0,\"track\":{\"name\":\"kitten_background\",\"settings\":{\"change\":\"background\"},\"url\":\"https://s3-mind-tracker.storage.yandexcloud.net/tracks/prod/4202f0622571733963ec8cb29947d20c3d374116b967344baf3003aee4608abf.mp3\",\"translationLanguages\":[]}}],\"translationLanguages\":[{\"title\":\"Gato\",\"description\":\"Cuando tengas el nivel adecuado de relajación, escucharás al gato ronronear.\",\"language\":{\"name\":\"Español\",\"isoCode\":\"es\"}},{\"title\":\"Kitten\",\"description\":\"When you have the right level of relaxation, you will hear the cat purring.\",\"language\":{\"name\":\"english\",\"isoCode\":\"en\"}},{\"title\":\"Котик\",\"description\":\"Когда у вас нужный уровень релаксации, вы будете слышать мурчание кота.\",\"language\":{\"name\":\"russian\",\"isoCode\":\"ru\"}}],\"training_type\":\"training\"},{\"name\":\"Campfire\",\"sampleUrl\":\"https://s3-mind-tracker.storage.yandexcloud.net/samples/prod/52143d9a0c0330e57ebc980b7b1fc05c5adb8aa85ba5e7419cfe1a7f0401d8cb.mp3\",\"imageUrl\":\"https://s3-mind-tracker.storage.yandexcloud.net/images/prod/1633da350d856b049439f67bcaf8a746047cb59a8a2eb9cec587daf232e22ad5.jpg\",\"playlistTracks\":[{\"trackOrder\":0,\"track\":{\"name\":\"campfire_crackle_campfire\",\"settings\":{\"change\":\"positive_feedback\"},\"url\":\"https://s3-mind-tracker.storage.yandexcloud.net/tracks/prod/175c7935d89190fcd1ac3e2ae1a282059baf100844c6b3c63d729743e1c6b57e.mp3\",\"translationLanguages\":[]}},{\"trackOrder\":0,\"track\":{\"name\":\"campfire_background\",\"settings\":{\"change\":\"background\"},\"url\":\"https://s3-mind-tracker.storage.yandexcloud.net/tracks/prod/d866f9a868d1f5485495e725a2567a43417bfe3340cb6c62f7a5353ebf2c7bcb.mp3\",\"translationLanguages\":[]}}],\"translationLanguages\":[{\"title\":\"Костер\",\"description\":\"Когда у вас нужный уровень релаксации, вы будете слышать потрескивание костра.\",\"language\":{\"name\":\"russian\",\"isoCode\":\"ru\"}},{\"title\":\"Campfire\",\"description\":\"When you have the right level of relaxation, you will hear the noise of the campfire.\",\"language\":{\"name\":\"english\",\"isoCode\":\"en\"}},{\"title\":\"Hoguera\",\"description\":\"Cuando estés en el nivel adecuado de relajación, escucharás el crepitar del fuego.\",\"language\":{\"name\":\"Español\",\"isoCode\":\"es\"}}],\"training_type\":\"training\"},{\"name\":\"Rain\",\"sampleUrl\":\"https://s3-mind-tracker.storage.yandexcloud.net/samples/prod/3ce81e50f3b593c25182ef63146363ed73e431dbfb91e3b33328c3b185cc15e0.mp3\",\"imageUrl\":\"https://s3-mind-tracker.storage.yandexcloud.net/images/prod/672a8c99de2ccfb2fa63449d2776d6a998586b49d00c063318342363ec89c3b2.jpg\",\"playlistTracks\":[{\"trackOrder\":0,\"track\":{\"name\":\"rain_light_rain\",\"settings\":{\"change\":\"positive_feedback\"},\"url\":\"https://s3-mind-tracker.storage.yandexcloud.net/tracks/prod/00db464ddee61716f8bc2098186a3e6cfa9f0deb6c782512a43e690c13027fc8.mp3\",\"translationLanguages\":[]}},{\"trackOrder\":0,\"track\":{\"name\":\"rain_heavy_rain\",\"settings\":{\"change\":\"negative_feedback\"},\"url\":\"https://s3-mind-tracker.storage.yandexcloud.net/tracks/prod/cc0ec0936dffbecd7d85ee3f8d9cd75f2943d61f714877f631c588059f556619.mp3\",\"translationLanguages\":[]}}],\"translationLanguages\":[{\"title\":\"Lluvia\",\"description\":\"Cuando esté en el nivel adecuado de relajación, escuchará una fuerte lluvia. De lo contrario, lluvia ligera.\",\"language\":{\"name\":\"Español\",\"isoCode\":\"es\"}},{\"title\":\"Дождь\",\"description\":\"Когда у вас нужный уровень релаксации, вы будете слышать сильный дождь. Иначе - легкий дождь.\",\"language\":{\"name\":\"russian\",\"isoCode\":\"ru\"}},{\"title\":\"Rain\",\"description\":\"When you have the right level of relaxation, you will hear heavy rain. Otherwise, light rain.\",\"language\":{\"name\":\"english\",\"isoCode\":\"en\"}}],\"training_type\":\"training\"},{\"name\":\"Meditation Base RU M\",\"sampleUrl\":\"https://s3-mind-tracker.storage.yandexcloud.net/samples/prod/4931e5900235b2c278ebddcdd03e3f7f7d0f7445a1eaf8abe8feba8d7f07e67a.mp3\",\"imageUrl\":\"https://s3-mind-tracker.storage.yandexcloud.net/images/prod/dde218ea151fa9df3700760d15263f0fa14bc8e09e959104b4fc3d5bebe4fc96.jpg\",\"playlistTracks\":[{\"trackOrder\":1,\"track\":{\"name\":\"meditation_base_ru_m_01\",\"settings\":{\"change\":\"guide\"},\"url\":\"https://s3-mind-tracker.storage.yandexcloud.net/tracks/prod/c53f8707b12303985f215532a9391709528b09e4f52dac503dd87ded5b1d435e.mp3\",\"translationLanguages\":[]}},{\"trackOrder\":2,\"track\":{\"name\":\"meditation_base_ru_m_02\",\"settings\":{\"change\":\"guide\"},\"url\":\"https://s3-mind-tracker.storage.yandexcloud.net/tracks/prod/320d02962093f5e3031b808c06674fb946c790cb273913e4720ee1bb446bd91d.mp3\",\"translationLanguages\":[]}},{\"trackOrder\":3,\"track\":{\"name\":\"meditation_base_ru_m_03\",\"settings\":{\"change\":\"guide\"},\"url\":\"https://s3-mind-tracker.storage.yandexcloud.net/tracks/prod/4d80c0654359dd329fca35e43340af253a6eadd5b8b538d54ec2252c85712c65.mp3\",\"translationLanguages\":[]}},{\"trackOrder\":4,\"track\":{\"name\":\"meditation_base_ru_m_04\",\"settings\":{\"change\":\"guide\"},\"url\":\"https://s3-mind-tracker.storage.yandexcloud.net/tracks/prod/4e4ea58b562036eb088ad15765e1bce6fa2aab6fa41043ed84dc683ec6defa0a.mp3\",\"translationLanguages\":[]}},{\"trackOrder\":5,\"track\":{\"name\":\"meditation_base_ru_m_05\",\"settings\":{\"change\":\"guide\"},\"url\":\"https://s3-mind-tracker.storage.yandexcloud.net/tracks/prod/40c80cb80424e10938e9f916634c66861362816af9942fcbc415f16f2a4ac360.mp3\",\"translationLanguages\":[]}},{\"trackOrder\":6,\"track\":{\"name\":\"meditation_base_ru_m_06\",\"settings\":{\"change\":\"guide\"},\"url\":\"https://s3-mind-tracker.storage.yandexcloud.net/tracks/prod/57e68d52a52e037d06613ca2ca35a0d5de86d6e444fbe0f9a78944addf3d0f18.mp3\",\"translationLanguages\":[]}},{\"trackOrder\":7,\"track\":{\"name\":\"meditation_base_ru_m_07\",\"settings\":{\"change\":\"guide\"},\"url\":\"https://s3-mind-tracker.storage.yandexcloud.net/tracks/prod/32253a6f93cf497fb1e6ded76994ee6b9306fe79e97cb4337eeb4fbcbde9e68b.mp3\",\"translationLanguages\":[]}},{\"trackOrder\":8,\"track\":{\"name\":\"meditation_base_ru_m_08\",\"settings\":{\"change\":\"guide\"},\"url\":\"https://s3-mind-tracker.storage.yandexcloud.net/tracks/prod/0699a85e88ddcbede38574d33753d1a87f2ae94673e1c5dec8629f81db844e02.mp3\",\"translationLanguages\":[]}},{\"trackOrder\":9,\"track\":{\"name\":\"meditation_base_ru_m_09\",\"settings\":{\"change\":\"guide\"},\"url\":\"https://s3-mind-tracker.storage.yandexcloud.net/tracks/prod/651352a220eff9880e74c012fd607e78356d9ef597cbae083aafa0e4950e61c1.mp3\",\"translationLanguages\":[]}},{\"trackOrder\":10,\"track\":{\"name\":\"meditation_base_ru_m_10\",\"settings\":{\"change\":\"guide\"},\"url\":\"https://s3-mind-tracker.storage.yandexcloud.net/tracks/prod/456d51340f595923d7620ec60a217224519e271f6b127b60677e73d93b76da48.mp3\",\"translationLanguages\":[]}},{\"trackOrder\":11,\"track\":{\"name\":\"meditation_base_ru_m_11\",\"settings\":{\"change\":\"guide\"},\"url\":\"https://s3-mind-tracker.storage.yandexcloud.net/tracks/prod/cb935862d6a39043bcd0e7798834ddba716525b51c762220782f3370db712e7f.mp3\",\"translationLanguages\":[]}},{\"trackOrder\":12,\"track\":{\"name\":\"meditation_base_ru_m_12\",\"settings\":{\"change\":\"guide\"},\"url\":\"https://s3-mind-tracker.storage.yandexcloud.net/tracks/prod/9cbb97544cdecf870b1b1cf7acdc39fc6f37eee53747bce8c50dfba224bf2e4b.mp3\",\"translationLanguages\":[]}},{\"trackOrder\":13,\"track\":{\"name\":\"meditation_base_ru_m_13\",\"settings\":{\"change\":\"guide\"},\"url\":\"https://s3-mind-tracker.storage.yandexcloud.net/tracks/prod/951b99db74d952689a5797b7a79c371b495448c074bbbda9efa53e27cf81dbe4.mp3\",\"translationLanguages\":[]}},{\"trackOrder\":14,\"track\":{\"name\":\"meditation_base_ru_m_14\",\"settings\":{\"change\":\"guide\"},\"url\":\"https://s3-mind-tracker.storage.yandexcloud.net/tracks/prod/bebe36f42b7a698efb2c4356efea70bc43014d5594656ec432b72682c2d47402.mp3\",\"translationLanguages\":[]}},{\"trackOrder\":15,\"track\":{\"name\":\"meditation_base_ru_m_15\",\"settings\":{\"change\":\"guide\"},\"url\":\"https://s3-mind-tracker.storage.yandexcloud.net/tracks/prod/fdce0d0f37c36ffbf01ab65a75ebb9bf5fd01be87381415e62a793e3943215df.mp3\",\"translationLanguages\":[]}},{\"trackOrder\":16,\"track\":{\"name\":\"meditation_base_ru_m_16\",\"settings\":{\"change\":\"guide\"},\"url\":\"https://s3-mind-tracker.storage.yandexcloud.net/tracks/prod/5a92850ba7e30bcca82cb28ddaf2417fa22fc692cad6b838c9ea1bda5f789f90.mp3\",\"translationLanguages\":[]}},{\"trackOrder\":17,\"track\":{\"name\":\"meditation_base_ru_m_17\",\"settings\":{\"change\":\"guide\"},\"url\":\"https://s3-mind-tracker.storage.yandexcloud.net/tracks/prod/15fd80df046665bf47eb88acf2d7ff6f0f40dbe09eb96bc2c16af9750d0237fd.mp3\",\"translationLanguages\":[]}},{\"trackOrder\":18,\"track\":{\"name\":\"meditation_base_ru_m_18\",\"settings\":{\"change\":\"guide\"},\"url\":\"https://s3-mind-tracker.storage.yandexcloud.net/tracks/prod/a64c6a1935899bb56e8d46ad8317932bac29ca5912bf02758c0c3b903cbc8b08.mp3\",\"translationLanguages\":[]}},{\"trackOrder\":19,\"track\":{\"name\":\"meditation_base_ru_m_19\",\"settings\":{\"change\":\"guide\"},\"url\":\"https://s3-mind-tracker.storage.yandexcloud.net/tracks/prod/99f9548a49a434637e41b109faf15289873ae32ee015b3b68024ab11e8de44d9.mp3\",\"translationLanguages\":[]}},{\"trackOrder\":20,\"track\":{\"name\":\"meditation_base_ru_m_20\",\"settings\":{\"change\":\"guide\"},\"url\":\"https://s3-mind-tracker.storage.yandexcloud.net/tracks/prod/3366f08ff6bbb51cf02fd0d22138e1eb9069bf6caacd621f73f3c5d62cf8320e.mp3\",\"translationLanguages\":[]}},{\"trackOrder\":21,\"track\":{\"name\":\"meditation_base_ru_m_21\",\"settings\":{\"change\":\"guide\"},\"url\":\"https://s3-mind-tracker.storage.yandexcloud.net/tracks/prod/39d9baaf83bee8aea9319b0b8174f4024741c280070a5c410723028402d1762d.mp3\",\"translationLanguages\":[]}},{\"trackOrder\":22,\"track\":{\"name\":\"meditation_base_ru_m_22\",\"settings\":{\"change\":\"guide\"},\"url\":\"https://s3-mind-tracker.storage.yandexcloud.net/tracks/prod/3de0a3850ca4030b8039e04efb9eb11a2878baf3701350d1d867fd5ab96bdf71.mp3\",\"translationLanguages\":[]}},{\"trackOrder\":23,\"track\":{\"name\":\"meditation_base_ru_m_23\",\"settings\":{\"change\":\"guide\"},\"url\":\"https://s3-mind-tracker.storage.yandexcloud.net/tracks/prod/14e5e9233992e9cf20b4a8994b2ffcadf946b8411e413053eea5db252f8c376c.mp3\",\"translationLanguages\":[]}},{\"trackOrder\":24,\"track\":{\"name\":\"meditation_base_ru_m_24\",\"settings\":{\"change\":\"guide\"},\"url\":\"https://s3-mind-tracker.storage.yandexcloud.net/tracks/prod/945f7efdb0620855c63178884ca797fc001ffab239dd7b064bf8e9a661bfa718.mp3\",\"translationLanguages\":[]}},{\"trackOrder\":25,\"track\":{\"name\":\"meditation_base_ru_m_25\",\"settings\":{\"change\":\"guide\"},\"url\":\"https://s3-mind-tracker.storage.yandexcloud.net/tracks/prod/722966b5a26c0b63a68ee78ef3729c546b434908c43de7500c12b9219ec06ab2.mp3\",\"translationLanguages\":[]}},{\"trackOrder\":0,\"track\":{\"name\":\"central_park_birds\",\"settings\":{\"change\":\"positive_feedback\"},\"url\":\"https://s3-mind-tracker.storage.yandexcloud.net/tracks/prod/82f525edd808113d3cd9e485d7e187ee2aa2fb9f83b7afa9ef9b3255dffa2344.mp3\",\"translationLanguages\":[]}}],\"translationLanguages\":[{\"title\":\"Базовая, мужской голос\",\"description\":\"Во время медитации вы услышите инструкции. Если у вас получается медитировать, вы будете слышать пение птиц.\",\"language\":{\"name\":\"russian\",\"isoCode\":\"ru\"}}],\"training_type\":\"meditation\"},{\"name\":\"Meditation Base RU W\",\"sampleUrl\":\"https://s3-mind-tracker.storage.yandexcloud.net/samples/prod/3342b60bdc105ca56e7736b1d8dbc793d4c95b4e988386a71dc977daad745353.mp3\",\"imageUrl\":\"https://s3-mind-tracker.storage.yandexcloud.net/images/prod/3eaa79fb399d2bf905515d17d4a39da73e43200dc041598feca0cf7e785fd032.jpg\",\"playlistTracks\":[{\"trackOrder\":1,\"track\":{\"name\":\"meditation_base_ru_w_01\",\"settings\":{\"change\":\"guide\"},\"url\":\"https://s3-mind-tracker.storage.yandexcloud.net/tracks/prod/754813e5b03e7f7c63a4686cbb21ce2fc4ca21c3b23f3860571793fb2a8eee77.mp3\",\"translationLanguages\":[]}},{\"trackOrder\":2,\"track\":{\"name\":\"meditation_base_ru_w_02\",\"settings\":{\"change\":\"guide\"},\"url\":\"https://s3-mind-tracker.storage.yandexcloud.net/tracks/prod/681adae68a1844415934185e11e11ed22a471bc93841ceafd18c077e49d6fe66.mp3\",\"translationLanguages\":[]}},{\"trackOrder\":3,\"track\":{\"name\":\"meditation_base_ru_w_03\",\"settings\":{\"change\":\"guide\"},\"url\":\"https://s3-mind-tracker.storage.yandexcloud.net/tracks/prod/2dacdba20332dc64f97ee6482a3beac205965821c95dc9276b8a7dcc2db17957.mp3\",\"translationLanguages\":[]}},{\"trackOrder\":4,\"track\":{\"name\":\"meditation_base_ru_w_04\",\"settings\":{\"change\":\"guide\"},\"url\":\"https://s3-mind-tracker.storage.yandexcloud.net/tracks/prod/57f5ebf2e84f9783a49010156478823184c17f695d54a5ce9dba73c4fa5affcb.mp3\",\"translationLanguages\":[]}},{\"trackOrder\":5,\"track\":{\"name\":\"meditation_base_ru_w_05\",\"settings\":{\"change\":\"guide\"},\"url\":\"https://s3-mind-tracker.storage.yandexcloud.net/tracks/prod/cfb1378ca25617f57e48ebd327dcfef17ba7f3feda71a53cb8c445cea190df48.mp3\",\"translationLanguages\":[]}},{\"trackOrder\":6,\"track\":{\"name\":\"meditation_base_ru_w_06\",\"settings\":{\"change\":\"guide\"},\"url\":\"https://s3-mind-tracker.storage.yandexcloud.net/tracks/prod/f96d6c3fed84ad9b813e48074e83b93dde495866612cb0a6f827443d2b74beaa.mp3\",\"translationLanguages\":[]}},{\"trackOrder\":7,\"track\":{\"name\":\"meditation_base_ru_w_07\",\"settings\":{\"change\":\"guide\"},\"url\":\"https://s3-mind-tracker.storage.yandexcloud.net/tracks/prod/bc95091cf0bdcc8a5a0a8f8936f6c505969b4018cde55443fa1c073b5ece64ed.mp3\",\"translationLanguages\":[]}},{\"trackOrder\":8,\"track\":{\"name\":\"meditation_base_ru_w_08\",\"settings\":{\"change\":\"guide\"},\"url\":\"https://s3-mind-tracker.storage.yandexcloud.net/tracks/prod/5159ddb4e0e4b11d43e6b48b5ccec5c3e953f923b9d13a4ff47889fd3384e69f.mp3\",\"translationLanguages\":[]}},{\"trackOrder\":9,\"track\":{\"name\":\"meditation_base_ru_w_09\",\"settings\":{\"change\":\"guide\"},\"url\":\"https://s3-mind-tracker.storage.yandexcloud.net/tracks/prod/58f50e431e2c10d39cca44303d7e2c7598f2194800c487ce7f112a3e0a0912d1.mp3\",\"translationLanguages\":[]}},{\"trackOrder\":10,\"track\":{\"name\":\"meditation_base_ru_w_10\",\"settings\":{\"change\":\"guide\"},\"url\":\"https://s3-mind-tracker.storage.yandexcloud.net/tracks/prod/a887ba21c63c01b5d1f5dc5f64f646404377f4ae5804c73b9f93ea60ec1d422b.mp3\",\"translationLanguages\":[]}},{\"trackOrder\":11,\"track\":{\"name\":\"meditation_base_ru_w_11\",\"settings\":{\"change\":\"guide\"},\"url\":\"https://s3-mind-tracker.storage.yandexcloud.net/tracks/prod/8595318e8af5483ee3998e35ca28d736f4b70a8863957d19202b6c838aca893a.mp3\",\"translationLanguages\":[]}},{\"trackOrder\":12,\"track\":{\"name\":\"meditation_base_ru_w_12\",\"settings\":{\"change\":\"guide\"},\"url\":\"https://s3-mind-tracker.storage.yandexcloud.net/tracks/prod/ca9957179a8c30409f0e7aa5a47493e5da2a072b640960bb01df9edb09fa112d.mp3\",\"translationLanguages\":[]}},{\"trackOrder\":13,\"track\":{\"name\":\"meditation_base_ru_w_13\",\"settings\":{\"change\":\"guide\"},\"url\":\"https://s3-mind-tracker.storage.yandexcloud.net/tracks/prod/c1c75e31c1e4accc656c91141455c033050fb175f3dbf5785390e9b700282828.mp3\",\"translationLanguages\":[]}},{\"trackOrder\":14,\"track\":{\"name\":\"meditation_base_ru_w_14\",\"settings\":{\"change\":\"guide\"},\"url\":\"https://s3-mind-tracker.storage.yandexcloud.net/tracks/prod/f3455d4c8d00e89c513bfbec4324de8ca12b3c1a0ef945cec2a6a909142f4362.mp3\",\"translationLanguages\":[]}},{\"trackOrder\":15,\"track\":{\"name\":\"meditation_base_ru_w_15\",\"settings\":{\"change\":\"guide\"},\"url\":\"https://s3-mind-tracker.storage.yandexcloud.net/tracks/prod/51e5a86193d2cca042726d3038f38b7b3db67370e3de566456cb37c3d907e693.mp3\",\"translationLanguages\":[]}},{\"trackOrder\":16,\"track\":{\"name\":\"meditation_base_ru_w_16\",\"settings\":{\"change\":\"guide\"},\"url\":\"https://s3-mind-tracker.storage.yandexcloud.net/tracks/prod/f21d386ec9e7d60e8892634de4d70487fe113b25681d01b26aaad34f682bd21f.mp3\",\"translationLanguages\":[]}},{\"trackOrder\":17,\"track\":{\"name\":\"meditation_base_ru_w_17\",\"settings\":{\"change\":\"guide\"},\"url\":\"https://s3-mind-tracker.storage.yandexcloud.net/tracks/prod/8ff460f67233b68baac5bbff86e5941d85a1e11c9bfb86f832fc6a3af793da4b.mp3\",\"translationLanguages\":[]}},{\"trackOrder\":18,\"track\":{\"name\":\"meditation_base_ru_w_18\",\"settings\":{\"change\":\"guide\"},\"url\":\"https://s3-mind-tracker.storage.yandexcloud.net/tracks/prod/ff67ee1dc016b08c1d2c5c7323d97101e7286f23a00d433d9973e7c0d8055de0.mp3\",\"translationLanguages\":[]}},{\"trackOrder\":19,\"track\":{\"name\":\"meditation_base_ru_w_19\",\"settings\":{\"change\":\"guide\"},\"url\":\"https://s3-mind-tracker.storage.yandexcloud.net/tracks/prod/fd28862d18c5e98bc4b186954f08efd99d320536e9b18e429e010ea7651255eb.mp3\",\"translationLanguages\":[]}},{\"trackOrder\":20,\"track\":{\"name\":\"meditation_base_ru_w_20\",\"settings\":{\"change\":\"guide\"},\"url\":\"https://s3-mind-tracker.storage.yandexcloud.net/tracks/prod/131351c7bae30fff3bd10d601092f0051e31a9ba812bfb5d4723a35d0cf01d7d.mp3\",\"translationLanguages\":[]}},{\"trackOrder\":21,\"track\":{\"name\":\"meditation_base_ru_w_21\",\"settings\":{\"change\":\"guide\"},\"url\":\"https://s3-mind-tracker.storage.yandexcloud.net/tracks/prod/74e1caa48143baa02a84fd59c8f8d65a4cf979b8e1c9547907ab7deabf3c3074.mp3\",\"translationLanguages\":[]}},{\"trackOrder\":22,\"track\":{\"name\":\"meditation_base_ru_w_22\",\"settings\":{\"change\":\"guide\"},\"url\":\"https://s3-mind-tracker.storage.yandexcloud.net/tracks/prod/0fe072f7d6f34f7b97aaf770d301fde7612b9b4a09d48e11bbbf88acb1f793dd.mp3\",\"translationLanguages\":[]}},{\"trackOrder\":23,\"track\":{\"name\":\"meditation_base_ru_w_23\",\"settings\":{\"change\":\"guide\"},\"url\":\"https://s3-mind-tracker.storage.yandexcloud.net/tracks/prod/00487fcbbafec5254852ad92a321d0b0d13514dcb9368faa8c470335f6d2437e.mp3\",\"translationLanguages\":[]}},{\"trackOrder\":24,\"track\":{\"name\":\"meditation_base_ru_w_24\",\"settings\":{\"change\":\"guide\"},\"url\":\"https://s3-mind-tracker.storage.yandexcloud.net/tracks/prod/5d290027902451e2362adec3a3a919e2b590a4f65a2a432992c8b8bf9ef3a4c6.mp3\",\"translationLanguages\":[]}},{\"trackOrder\":25,\"track\":{\"name\":\"meditation_base_ru_w_25\",\"settings\":{\"change\":\"guide\"},\"url\":\"https://s3-mind-tracker.storage.yandexcloud.net/tracks/prod/f8a604f97cb12333fe71fe9bfc8dc9756aae43c3c0c32c48599ebd9ceab29392.mp3\",\"translationLanguages\":[]}},{\"trackOrder\":0,\"track\":{\"name\":\"kitten_cat_purring\",\"settings\":{\"change\":\"positive_feedback\"},\"url\":\"https://s3-mind-tracker.storage.yandexcloud.net/tracks/prod/a375712d563da9d56479ab04e65bd2012faba043cbe2df92511a28ee21eff9d7.mp3\",\"translationLanguages\":[]}}],\"translationLanguages\":[{\"title\":\"Базовая, женский голос\",\"description\":\"Во время медитации вы услышите инструкции. Если у вас получается медитировать, вы будете слышать мурчание кота.\",\"language\":{\"name\":\"russian\",\"isoCode\":\"ru\"}}],\"training_type\":\"meditation\"},{\"name\":\"Meditation Base EN M\",\"sampleUrl\":\"https://s3-mind-tracker.storage.yandexcloud.net/samples/prod/4dac9f71d691584b7c332f906b97176e3530c457b8efce3243c9561da422c060.mp3\",\"imageUrl\":\"https://s3-mind-tracker.storage.yandexcloud.net/images/prod/e05393f00d20a3d3ef9366f8d1d246df6f17c3ff9eb424f9048d4cbd9dec72f3.jpg\",\"playlistTracks\":[{\"trackOrder\":1,\"track\":{\"name\":\"meditation_base_en_m_01\",\"settings\":{\"change\":\"guide\"},\"url\":\"https://s3-mind-tracker.storage.yandexcloud.net/tracks/prod/29425ac3cc0796b07c2d6f56314126fedeb54472df9d68e6b0e2ee1eccf1adc9.mp3\",\"translationLanguages\":[]}},{\"trackOrder\":2,\"track\":{\"name\":\"meditation_base_en_m_02\",\"settings\":{\"change\":\"guide\"},\"url\":\"https://s3-mind-tracker.storage.yandexcloud.net/tracks/prod/ad3964f082e940fd73c4a0c26c11f2b6e945b386005e393827eff457ab2feb61.mp3\",\"translationLanguages\":[]}},{\"trackOrder\":3,\"track\":{\"name\":\"meditation_base_en_m_03\",\"settings\":{\"change\":\"guide\"},\"url\":\"https://s3-mind-tracker.storage.yandexcloud.net/tracks/prod/14196c2853482dc07d4da944517009632899755708d888162cac2690bd9e311d.mp3\",\"translationLanguages\":[]}},{\"trackOrder\":4,\"track\":{\"name\":\"meditation_base_en_m_04\",\"settings\":{\"change\":\"guide\"},\"url\":\"https://s3-mind-tracker.storage.yandexcloud.net/tracks/prod/f35465e615ec69a878b7fa57142a2a71ad4b48519cdc12edf6c87bc6c90acdba.mp3\",\"translationLanguages\":[]}},{\"trackOrder\":5,\"track\":{\"name\":\"meditation_base_en_m_05\",\"settings\":{\"change\":\"guide\"},\"url\":\"https://s3-mind-tracker.storage.yandexcloud.net/tracks/prod/08e91247a454e475af7046b2b1457558f595396aa6e7d43eda2b9a41e269a623.mp3\",\"translationLanguages\":[]}},{\"trackOrder\":6,\"track\":{\"name\":\"meditation_base_en_m_06\",\"settings\":{\"change\":\"guide\"},\"url\":\"https://s3-mind-tracker.storage.yandexcloud.net/tracks/prod/7b57ed909d6bec4b51d5118e4facd431ee4919a9ccdb892cd901aae45355768a.mp3\",\"translationLanguages\":[]}},{\"trackOrder\":7,\"track\":{\"name\":\"meditation_base_en_m_07\",\"settings\":{\"change\":\"guide\"},\"url\":\"https://s3-mind-tracker.storage.yandexcloud.net/tracks/prod/966c688cc3885a1131b4a218717e5a244d3cc8aad690389667815f8b04bc11e4.mp3\",\"translationLanguages\":[]}},{\"trackOrder\":8,\"track\":{\"name\":\"meditation_base_en_m_08\",\"settings\":{\"change\":\"guide\"},\"url\":\"https://s3-mind-tracker.storage.yandexcloud.net/tracks/prod/c0983d6e7cc1facb7f38808ceea90c91f147961e11fc09bdb99dfbc47f4be032.mp3\",\"translationLanguages\":[]}},{\"trackOrder\":9,\"track\":{\"name\":\"meditation_base_en_m_09\",\"settings\":{\"change\":\"guide\"},\"url\":\"https://s3-mind-tracker.storage.yandexcloud.net/tracks/prod/75a041aa640ada1c1590eec466ed45621f38b71477f1fd2ae244a6e665a15a55.mp3\",\"translationLanguages\":[]}},{\"trackOrder\":10,\"track\":{\"name\":\"meditation_base_en_m_10\",\"settings\":{\"change\":\"guide\"},\"url\":\"https://s3-mind-tracker.storage.yandexcloud.net/tracks/prod/432e05d20e755b04bb9dc8c611950c4f15f3af7ce1ee4c8d970fb1dbbf44da57.mp3\",\"translationLanguages\":[]}},{\"trackOrder\":11,\"track\":{\"name\":\"meditation_base_en_m_11\",\"settings\":{\"change\":\"guide\"},\"url\":\"https://s3-mind-tracker.storage.yandexcloud.net/tracks/prod/3af8077e6dba8ffac502633ba415752c1879a623e76518231f0fcbf4a933b9fe.mp3\",\"translationLanguages\":[]}},{\"trackOrder\":12,\"track\":{\"name\":\"meditation_base_en_m_12\",\"settings\":{\"change\":\"guide\"},\"url\":\"https://s3-mind-tracker.storage.yandexcloud.net/tracks/prod/c51f8c9a29d65f13d3922fe5eb7707089478ac6f149e88626be8bc967547e8a8.mp3\",\"translationLanguages\":[]}},{\"trackOrder\":13,\"track\":{\"name\":\"meditation_base_en_m_13\",\"settings\":{\"change\":\"guide\"},\"url\":\"https://s3-mind-tracker.storage.yandexcloud.net/tracks/prod/35f78d8ae2ea04a76615c42feb2c5ccc58454daee02095ce561c5b96df6ca4ac.mp3\",\"translationLanguages\":[]}},{\"trackOrder\":14,\"track\":{\"name\":\"meditation_base_en_m_14\",\"settings\":{\"change\":\"guide\"},\"url\":\"https://s3-mind-tracker.storage.yandexcloud.net/tracks/prod/15698df419df5b04f8052ab5eb6d5b911991a67086ae381a97d179a65c0d3dd5.mp3\",\"translationLanguages\":[]}},{\"trackOrder\":15,\"track\":{\"name\":\"meditation_base_en_m_15\",\"settings\":{\"change\":\"guide\"},\"url\":\"https://s3-mind-tracker.storage.yandexcloud.net/tracks/prod/c8d6bda9b3fd8709f7d278610e450a811825cc14de667cff242fc97f33a575fc.mp3\",\"translationLanguages\":[]}},{\"trackOrder\":16,\"track\":{\"name\":\"meditation_base_en_m_16\",\"settings\":{\"change\":\"guide\"},\"url\":\"https://s3-mind-tracker.storage.yandexcloud.net/tracks/prod/26ce1806ae90ad5538b1dc8d6f53f9f681184999dc777a1ba918ea88a8c217c5.mp3\",\"translationLanguages\":[]}},{\"trackOrder\":17,\"track\":{\"name\":\"meditation_base_en_m_17\",\"settings\":{\"change\":\"guide\"},\"url\":\"https://s3-mind-tracker.storage.yandexcloud.net/tracks/prod/f139d172f79421968721fcc4cf2dbd2478ffe4c27578b63e46e32a72dceec78a.mp3\",\"translationLanguages\":[]}},{\"trackOrder\":18,\"track\":{\"name\":\"meditation_base_en_m_18\",\"settings\":{\"change\":\"guide\"},\"url\":\"https://s3-mind-tracker.storage.yandexcloud.net/tracks/prod/4cce7fd12ce073452eab6a7e0b056d5e00b35d6517ef9c7536769934f805597e.mp3\",\"translationLanguages\":[]}},{\"trackOrder\":19,\"track\":{\"name\":\"meditation_base_en_m_19\",\"settings\":{\"change\":\"guide\"},\"url\":\"https://s3-mind-tracker.storage.yandexcloud.net/tracks/prod/0930e3a21182c00b3eed09445c74c6a28a190ea82a6d694825b730bdebadc9c9.mp3\",\"translationLanguages\":[]}},{\"trackOrder\":20,\"track\":{\"name\":\"meditation_base_en_m_20\",\"settings\":{\"change\":\"guide\"},\"url\":\"https://s3-mind-tracker.storage.yandexcloud.net/tracks/prod/9ddfe3d927669e542f182422723d009590deb8e8ee8a032030283e9290117da6.mp3\",\"translationLanguages\":[]}},{\"trackOrder\":21,\"track\":{\"name\":\"meditation_base_en_m_21\",\"settings\":{\"change\":\"guide\"},\"url\":\"https://s3-mind-tracker.storage.yandexcloud.net/tracks/prod/2a6d20a9504580cda9e3c859267f50bc5bfae5d31ee2569df0baae13d8c288dc.mp3\",\"translationLanguages\":[]}},{\"trackOrder\":22,\"track\":{\"name\":\"meditation_base_en_m_22\",\"settings\":{\"change\":\"guide\"},\"url\":\"https://s3-mind-tracker.storage.yandexcloud.net/tracks/prod/b415d0ec50e8e4c3e1db531b67847b75faffd4a413034499c45e905eb92973d8.mp3\",\"translationLanguages\":[]}},{\"trackOrder\":0,\"track\":{\"name\":\"central_park_birds\",\"settings\":{\"change\":\"positive_feedback\"},\"url\":\"https://s3-mind-tracker.storage.yandexcloud.net/tracks/prod/82f525edd808113d3cd9e485d7e187ee2aa2fb9f83b7afa9ef9b3255dffa2344.mp3\",\"translationLanguages\":[]}}],\"translationLanguages\":[{\"title\":\"Voz masculina básica\",\"description\":\"Durante la meditación, escuchará instrucciones. Si puedes meditar, escucharás el canto de los pájaros.\",\"language\":{\"name\":\"Español\",\"isoCode\":\"es\"}},{\"title\":\"Basic, male voice\",\"description\":\"During meditation, you will hear instructions. If you can meditate, you will hear the birds singing.\",\"language\":{\"name\":\"english\",\"isoCode\":\"en\"}}],\"training_type\":\"meditation\"},{\"name\":\"Tracking_calm\",\"sampleUrl\":\"https://s3-mind-tracker.storage.yandexcloud.net/samples/prod/b68a0b859f6e04ecd8a72a9bc168ef54b412061674b7bee8b08cb26690fde49e.mp3\",\"imageUrl\":\"https://s3-mind-tracker.storage.yandexcloud.net/images/prod/e2a932579c62a23187f4ce86fcfe1c18c41b4d4859edd801b7cf582030d6b0c5.jpg\",\"playlistTracks\":[{\"trackOrder\":0,\"track\":{\"name\":\"central_park_background\",\"settings\":{\"change\":\"background\"},\"url\":\"https://s3-mind-tracker.storage.yandexcloud.net/tracks/prod/250c4c24198ec5e4ffd373ba074105ca3b650a214a1421aa9eb7f1b17be65d66.mp3\",\"translationLanguages\":[]}}],\"translationLanguages\":[{\"title\":\"Спокойная музыка\",\"description\":\"Спокойная музыка будет оповещать о вашем состоянии\",\"language\":{\"name\":\"russian\",\"isoCode\":\"ru\"}},{\"title\":\"Musica tranquila\",\"description\":\"La música tranquila te notificará de tu condición.\",\"language\":{\"name\":\"Español\",\"isoCode\":\"es\"}},{\"title\":\"Calm music\",\"description\":\"Calm music will alert you about your condition\",\"language\":{\"name\":\"english\",\"isoCode\":\"en\"}}],\"training_type\":\"rest\"},{\"name\":\"Tracking_Birdsong\",\"sampleUrl\":\"https://s3-mind-tracker.storage.yandexcloud.net/samples/prod/85ef245abe4035234de5884b5e6d4c2ce9fdb8db62fbed03eaa628280232138f.mp3\",\"imageUrl\":\"https://s3-mind-tracker.storage.yandexcloud.net/images/prod/fb3874ec787f8c5cc428a71dc5fc338934724894e8d208bc7837415bf94d4e95.jpg\",\"playlistTracks\":[{\"trackOrder\":0,\"track\":{\"name\":\"central_park_birds\",\"settings\":{\"change\":\"positive_feedback\"},\"url\":\"https://s3-mind-tracker.storage.yandexcloud.net/tracks/prod/82f525edd808113d3cd9e485d7e187ee2aa2fb9f83b7afa9ef9b3255dffa2344.mp3\",\"translationLanguages\":[]}}],\"translationLanguages\":[{\"title\":\"Pájaros cantando\",\"description\":\"El canto de los pájaros te avisará de tu estado\",\"language\":{\"name\":\"Español\",\"isoCode\":\"es\"}},{\"title\":\"Birdsong\",\"description\":\"Birdsong will alert you about your condition\",\"language\":{\"name\":\"english\",\"isoCode\":\"en\"}},{\"title\":\"Пение птиц\",\"description\":\"Пение птиц будет оповещать о вашем состоянии\",\"language\":{\"name\":\"russian\",\"isoCode\":\"ru\"}}],\"training_type\":\"rest\"},{\"name\":\"Tracking_Cat_purring\",\"sampleUrl\":\"https://s3-mind-tracker.storage.yandexcloud.net/samples/prod/27d9e55bae03132e2fce18c0343ec22f36cf16ed8d38e14a09b6e9accc39bb3f.mp3\",\"imageUrl\":\"https://s3-mind-tracker.storage.yandexcloud.net/images/prod/085d14ba448b6e809104e5403bed971b4b96d93b815759c21a9766ed2194face.jpg\",\"playlistTracks\":[{\"trackOrder\":0,\"track\":{\"name\":\"kitten_cat_purring\",\"settings\":{\"change\":\"positive_feedback\"},\"url\":\"https://s3-mind-tracker.storage.yandexcloud.net/tracks/prod/a375712d563da9d56479ab04e65bd2012faba043cbe2df92511a28ee21eff9d7.mp3\",\"translationLanguages\":[]}}],\"translationLanguages\":[{\"title\":\"Cat purring\",\"description\":\"Cat purring will alert you about your condition\",\"language\":{\"name\":\"english\",\"isoCode\":\"en\"}},{\"title\":\"Gato ronroneando\",\"description\":\"El ronroneo de un gato te avisará de tu estado\",\"language\":{\"name\":\"Español\",\"isoCode\":\"es\"}},{\"title\":\"Мурчание кота\",\"description\":\"Мурчание кота будет оповещать о вашем состоянии\",\"language\":{\"name\":\"russian\",\"isoCode\":\"ru\"}}],\"training_type\":\"slots\"},{\"name\":\"Tracking_Restless\",\"sampleUrl\":\"https://s3-mind-tracker.storage.yandexcloud.net/samples/prod/4c0fcaff987d0efc2dacdfad3dbe9db95553f73df57b692817f5884179b42e56.mp3\",\"imageUrl\":\"https://s3-mind-tracker.storage.yandexcloud.net/images/prod/50115ef4df5ebbbd7eeea4369063f3d585637482fac3e935722ad625cbf7dcd9.jpg\",\"playlistTracks\":[{\"trackOrder\":0,\"track\":{\"name\":\"Tracking_restless\",\"settings\":{\"change\":\"background\"},\"url\":\"https://s3-mind-tracker.storage.yandexcloud.net/tracks/prod/e643d4ad71efc4c4643663f6c44cb180d587550bb9fda80baa80d26dec388578.mp3\",\"translationLanguages\":[]}}],\"translationLanguages\":[{\"title\":\"Musica inquieta\",\"description\":\"La música inquieta te avisará de tu estado\",\"language\":{\"name\":\"Español\",\"isoCode\":\"es\"}},{\"title\":\"Restless music\",\"description\":\"Restless music will alert you about your condition\",\"language\":{\"name\":\"english\",\"isoCode\":\"en\"}},{\"title\":\"Беспокойная музыка\",\"description\":\"Беспокойная музыка будет оповещать о вашем состоянии\",\"language\":{\"name\":\"russian\",\"isoCode\":\"ru\"}}],\"training_type\":\"slots\"},{\"name\":\"Tracking_Disturbing\",\"sampleUrl\":\"https://s3-mind-tracker.storage.yandexcloud.net/samples/prod/6c3001f799740671e88fd64d110d54fc0bf07290cc2afaa41516569830f4c9b4.mp3\",\"imageUrl\":\"https://s3-mind-tracker.storage.yandexcloud.net/images/prod/bd6fa6c37f6b0c9ebfc7dce6b33a2c0f638ab57d7ba3e1350e354487e04e0772.jpg\",\"playlistTracks\":[{\"trackOrder\":0,\"track\":{\"name\":\"Tracking_disturbing\",\"settings\":{\"change\":\"background\"},\"url\":\"https://s3-mind-tracker.storage.yandexcloud.net/tracks/prod/5f2c7f4020f0b27463d6b9418acb6e923a348ff1ba21a7a3c06a4b7f65c9eb9e.mp3\",\"translationLanguages\":[]}}],\"translationLanguages\":[{\"title\":\"Disturbing music\",\"description\":\"Disturbing music will alert you about your condition\",\"language\":{\"name\":\"english\",\"isoCode\":\"en\"}},{\"title\":\"Тревожная музыка\",\"description\":\"Тревожная музыка будет оповещать о вашем состоянии\",\"language\":{\"name\":\"russian\",\"isoCode\":\"ru\"}},{\"title\":\"Musica perturbadora\",\"description\":\"La música alarmante te notificará de tu condición.\",\"language\":{\"name\":\"Español\",\"isoCode\":\"es\"}}],\"training_type\":\"slots\"},{\"name\":\"Tracking_calm_campfire_background\",\"sampleUrl\":\"https://s3-mind-tracker.storage.yandexcloud.net/samples/prod/2e1906ccd2266aefb32db6edfdcf64b844ac3ea2da583c9984ec27b0e4061f94.mp3\",\"imageUrl\":\"https://s3-mind-tracker.storage.yandexcloud.net/images/prod/a1d29a8845c5b8e16b04e57c0a0b7d7088665c429d01c79f6be0a02e8eb80c26.jpg\",\"playlistTracks\":[{\"trackOrder\":0,\"track\":{\"name\":\"campfire_background\",\"settings\":{\"change\":\"background\"},\"url\":\"https://s3-mind-tracker.storage.yandexcloud.net/tracks/prod/d866f9a868d1f5485495e725a2567a43417bfe3340cb6c62f7a5353ebf2c7bcb.mp3\",\"translationLanguages\":[]}}],\"translationLanguages\":[{\"title\":\"Ambient music\",\"description\":\"Ambient music will alert you about your condition\",\"language\":{\"name\":\"english\",\"isoCode\":\"en\"}},{\"title\":\"Ambiente agradable\",\"description\":\"Una agradable música ambiental te avisará de tu estado.\",\"language\":{\"name\":\"Español\",\"isoCode\":\"es\"}},{\"title\":\"Приятный эмбиент\",\"description\":\"Приятный эмбиент будет оповещать о вашем состоянии\",\"language\":{\"name\":\"russian\",\"isoCode\":\"ru\"}}],\"training_type\":\"rest\"},{\"name\":\"Rest_Basic_Playlist\",\"sampleUrl\":\"https://s3-mind-tracker.storage.yandexcloud.net/samples/prod/7a5d6efc60b90a8c2284e73bb02c95399067f64a275a2333dc5f4d626fa4e5e7.mp3\",\"imageUrl\":\"https://s3-mind-tracker.storage.yandexcloud.net/images/prod/fc258221c6ec6c111a9aac268af816f720c16903a46a1e705bdf06c64387c74a.jpg\",\"playlistTracks\":[{\"trackOrder\":1,\"track\":{\"name\":\"central_park_background\",\"settings\":{\"change\":\"background\"},\"url\":\"https://s3-mind-tracker.storage.yandexcloud.net/tracks/prod/250c4c24198ec5e4ffd373ba074105ca3b650a214a1421aa9eb7f1b17be65d66.mp3\",\"translationLanguages\":[]}},{\"trackOrder\":1,\"track\":{\"name\":\"central_park_birds\",\"settings\":{\"change\":\"positive_feedback\"},\"url\":\"https://s3-mind-tracker.storage.yandexcloud.net/tracks/prod/82f525edd808113d3cd9e485d7e187ee2aa2fb9f83b7afa9ef9b3255dffa2344.mp3\",\"translationLanguages\":[]}},{\"trackOrder\":2,\"track\":{\"name\":\"kitten_cat_purring\",\"settings\":{\"change\":\"positive_feedback\"},\"url\":\"https://s3-mind-tracker.storage.yandexcloud.net/tracks/prod/a375712d563da9d56479ab04e65bd2012faba043cbe2df92511a28ee21eff9d7.mp3\",\"translationLanguages\":[]}},{\"trackOrder\":2,\"track\":{\"name\":\"kitten_background\",\"settings\":{\"change\":\"background\"},\"url\":\"https://s3-mind-tracker.storage.yandexcloud.net/tracks/prod/4202f0622571733963ec8cb29947d20c3d374116b967344baf3003aee4608abf.mp3\",\"translationLanguages\":[]}},{\"trackOrder\":3,\"track\":{\"name\":\"rain_light_rain\",\"settings\":{\"change\":\"positive_feedback\"},\"url\":\"https://s3-mind-tracker.storage.yandexcloud.net/tracks/prod/00db464ddee61716f8bc2098186a3e6cfa9f0deb6c782512a43e690c13027fc8.mp3\",\"translationLanguages\":[]}},{\"trackOrder\":4,\"track\":{\"name\":\"campfire_crackle_campfire\",\"settings\":{\"change\":\"positive_feedback\"},\"url\":\"https://s3-mind-tracker.storage.yandexcloud.net/tracks/prod/175c7935d89190fcd1ac3e2ae1a282059baf100844c6b3c63d729743e1c6b57e.mp3\",\"translationLanguages\":[]}}],\"translationLanguages\":[{\"title\":\"Lista de reproducción básica\",\"description\":\"Escuche el canto de los pájaros, el ronroneo de un gato, el sonido de la lluvia y el crepitar del fuego.\",\"language\":{\"name\":\"Español\",\"isoCode\":\"es\"}},{\"title\":\"Базовый плейлист\",\"description\":\"Добивайтесь пения птиц, мурчания кота, звука дождя и треска костра\",\"language\":{\"name\":\"russian\",\"isoCode\":\"ru\"}},{\"title\":\"Basic Playlist\",\"description\":\"Achieve the singing of birds, the purring of a cat, the sound of rain and the crackle of a campfire\",\"language\":{\"name\":\"english\",\"isoCode\":\"en\"}}],\"training_type\":\"sleeping\"}]",
  "GUEST_MODE_IS_DEVICE_RESTRICTED": false,
  "USER_ID": 11745,
  "ACCESS_TOKEN": "eyJhbGciOiJIUzI1NiIsInR5cCI6IkpXVCJ9.eyJpZCI6MTE3NDUsInByb2R1Y3RJZCI6MSwiZGV2aWNlSWQiOm51bGwsImV4cCI6MTc3MjcxMzM3N30.08WD2U1vgRW2_pniNe6Li4NiIWvx65VLn3OuAYdJxWk",
  "REFRESH_TOKEN": "81600a59-d983-426c-ac52-5acac2390ed0"
}